btsf/__init__.py
btsf/btsf.py
btsf/cli.py
btsf/exceptions.py
btsf/intro.py
btsf/metric.py
btsf/util.py
btsf-1.0.1.dist-info/METADATA
btsf-1.0.1.dist-info/WHEEL
btsf-1.0.1.dist-info/entry_points.txt
btsf-1.0.1.dist-info/top_level.txt
btsf-1.0.1.dist-info/zip-safe
btsf-1.0.1.dist-info/RECORD
