Metadata-Version: 2.1
Name: btsf
Version: 1.0.1
Summary: btsf (for Binary Time Series File) is a package to store your data in a condensed and fast yet flexible way.
Home-page: https://github.com/pklaus/btsf
Author: Philipp Klaus
Author-email: philipp.l.klaus@web.de
License: GPL
Keywords: binary,time series,file,storage
Platform: any
Classifier: Development Status :: 4 - Beta
Classifier: Operating System :: OS Independent
Classifier: License :: OSI Approved :: GNU General Public License v3 or later (GPLv3+)
Classifier: Programming Language :: Python
Classifier: Programming Language :: Python :: 3
Classifier: Topic :: System :: Archiving :: Compression
Classifier: Topic :: Office/Business :: Financial
Classifier: Topic :: Scientific/Engineering
Requires-Dist: attrs
Provides-Extra: tests
Requires-Dist: pytest ; extra == 'tests'
Provides-Extra: to_numpy
Requires-Dist: numpy ; extra == 'to_numpy'
Provides-Extra: to_pandas
Requires-Dist: pandas ; extra == 'to_pandas'
